cultural_japan_utils/__init__.py
cultural_japan_utils/_modidx.py
cultural_japan_utils/api.py
cultural_japan_utils/item.py
cultural_japan_utils-0.0.3.dist-info/LICENSE
cultural_japan_utils-0.0.3.dist-info/METADATA
cultural_japan_utils-0.0.3.dist-info/WHEEL
cultural_japan_utils-0.0.3.dist-info/entry_points.txt
cultural_japan_utils-0.0.3.dist-info/top_level.txt
cultural_japan_utils-0.0.3.dist-info/RECORD
